iverilog/fsm.v
module fsm(number, clk, rst);
output [2:0] number;
input clk, rst;

wire qa, qb, qc, qa_c, qb_c, qc_c;
wire da, db, dc;
wire [1:0]cnt;
wire cnt_en;

flipflop a(qa, qa_c, clk, da, rst);
flipflop b(qb, qb_c, clk, db, rst);
flipflop c(qc, qc_c, clk, dc, rst);
counter count(cnt, clk, cnt_en);
assign cnt_en = qa_c&qb&qc;
assign da = qa_c&((qb_c&qc_c)|(qb&qc&cnt[0]&cnt[1]));
assign db = qa_c&qc;
assign dc = (qa_c&qb_c)|(qc&((qa&qb_c)|(qa_c&qb&!(cnt[0]&cnt[1]))));

assign number[2] = qa;
assign number[1] = qb;
assign number[0] = qc;

endmodule

module counter(counter, clk, rst);
output [1:0]counter;
input clk, rst;

wire c0_in, c1_in;
wire q0, q1, q0_c, q1_c;

flipflop cnt0(q0, q0_c, clk, c0_in, rst);
flipflop cnt1(q1, q1_c, clk, c1_in, rst);

assign c1_in = q1_c&q0;
assign c0_in = q1_c;
assign counter[0] = q0;
assign counter[1] = q1;

endmodule

module flipflop(Q, Qc, CLK, D, RST);
input CLK, D, RST;
output Q;
output Qc;

wire S, R;
wire Sc, Rc;

nand g1(Sc, Rc, S);
nand g2(S, Sc, CLK, RST);
nand g3(R, Rc, CLK);
nand g4(Rc, R, D, RST);

nand g5(Q, Qc, S);
nand g6(Qc, Q, R, RST);

endmodule

iverilog/final_mock2/mock2.v
`include "../fsm.v"

module mock2(result, clk, rst);
output [4:0] result;
input clk, rst;

wire [2:0]num;
wire [4:0]new;
wire [4:0]acc, lastAcc;
wire acc_rst;

fsm f(num, clk, rst);
decoder dec(new, num);
fiveBitAdder adder(acc, new, lastAcc);
accDelay delay(lastAcc, acc, clk, acc_rst);
assign acc_rst = !(!num[2]&!num[1]&!num[0])&rst;
assign result = acc;

endmodule



module decoder(out, in);
output [4:0]out;
input [2:0]in;

assign out[4:3] = 2'b00;
assign out[2:0] = in[2:0];

endmodule

module fiveBitAdder(sum, a, b);
output [4:0] sum;
input [4:0] a, b;

assign sum = a+b;
endmodule

module accDelay(out, in, clk, rst);
output [4:0]out;
input [4:0]in;
input clk, rst;
flipflop f0(out[0], , clk, in[0], rst);
flipflop f1(out[1], , clk, in[1], rst);
flipflop f2(out[2], , clk, in[2], rst);
flipflop f3(out[3], , clk, in[3], rst);
flipflop f4(out[4], , clk, in[4], rst);
endmodule

iverilog/final_mock2/testbench.v
`timescale 1ns/1ns
`define CYCLE 10

module testbench();
reg CLK, RST;
wire [4:0]result;

mock2 mock(.result(result), .clk(CLK), .rst(RST));
	
always begin #`CYCLE CLK = ~CLK; end
initial begin
	$dumpfile("result.vcd");
	$dumpvars;
end

initial begin
#0
	RST = 0;
	CLK = 0;
#20
	RST = 1;
#500
	RST = 0;
	$finish;
end
endmodule

iverilog/final_mock2/result.vcd
$date
	Fri Jan 11 05:48:55 2019
$end
$version
	Icarus Verilog
$end
$timescale
	1ns
$end
$scope module testbench $end
$var wire 5 ! result [4:0] $end
$var reg 1 " CLK $end
$var reg 1 # RST $end
$scope module mock $end
$var wire 5 $ acc [4:0] $end
$var wire 1 % acc_rst $end
$var wire 1 & clk $end
$var wire 5 ' lastAcc [4:0] $end
$var wire 5 ( new [4:0] $end
$var wire 3 ) num [2:0] $end
$var wire 5 * result [4:0] $end
$var wire 1 + rst $end
$scope module f $end
$var wire 1 & clk $end
$var wire 2 , cnt [1:0] $end
$var wire 1 - cnt_en $end
$var wire 1 . da $end
$var wire 1 / db $end
$var wire 1 0 dc $end
$var wire 3 1 number [2:0] $end
$var wire 1 2 qa $end
$var wire 1 3 qa_c $end
$var wire 1 4 qb $end
$var wire 1 5 qb_c $end
$var wire 1 6 qc $end
$var wire 1 7 qc_c $end
$var wire 1 + rst $end
$scope module a $end
$var wire 1 & CLK $end
$var wire 1 . D $end
$var wire 1 2 Q $end
$var wire 1 3 Qc $end
$var wire 1 8 R $end
$var wire 1 + RST $end
$var wire 1 9 Rc $end
$var wire 1 : S $end
$var wire 1 ; Sc $end
$upscope $end
$scope module b $end
$var wire 1 & CLK $end
$var wire 1 / D $end
$var wire 1 4 Q $end
$var wire 1 5 Qc $end
$var wire 1 < R $end
$var wire 1 + RST $end
$var wire 1 = Rc $end
$var wire 1 > S $end
$var wire 1 ? Sc $end
$upscope $end
$scope module c $end
$var wire 1 & CLK $end
$var wire 1 0 D $end
$var wire 1 6 Q $end
$var wire 1 7 Qc $end
$var wire 1 @ R $end
$var wire 1 + RST $end
$var wire 1 A Rc $end
$var wire 1 B S $end
$var wire 1 C Sc $end
$upscope $end
$scope module count $end
$var wire 1 D c0_in $end
$var wire 1 E c1_in $end
$var wire 1 & clk $end
$var wire 2 F counter [1:0] $end
$var wire 1 G q0 $end
$var wire 1 H q0_c $end
$var wire 1 I q1 $end
$var wire 1 J q1_c $end
$var wire 1 - rst $end
$scope module cnt0 $end
$var wire 1 & CLK $end
$var wire 1 D D $end
$var wire 1 G Q $end
$var wire 1 H Qc $end
$var wire 1 K R $end
$var wire 1 - RST $end
$var wire 1 L Rc $end
$var wire 1 M S $end
$var wire 1 N Sc $end
$upscope $end
$scope module cnt1 $end
$var wire 1 & CLK $end
$var wire 1 E D $end
$var wire 1 I Q $end
$var wire 1 J Qc $end
$var wire 1 O R $end
$var wire 1 - RST $end
$var wire 1 P Rc $end
$var wire 1 Q S $end
$var wire 1 R Sc $end
$upscope $end
$upscope $end
$upscope $end
$scope module dec $end
$var wire 3 S in [2:0] $end
$var wire 5 T out [4:0] $end
$upscope $end
$scope module adder $end
$var wire 5 U a [4:0] $end
$var wire 5 V b [4:0] $end
$var wire 5 W sum [4:0] $end
$upscope $end
$scope module delay $end
$var wire 1 & clk $end
$var wire 5 X in [4:0] $end
$var wire 5 Y out [4:0] $end
$var wire 1 % rst $end
$scope module f0 $end
$var wire 1 & CLK $end
$var wire 1 Z D $end
$var wire 1 [ Q $end
$var wire 1 \ Qc $end
$var wire 1 ] R $end
$var wire 1 % RST $end
$var wire 1 ^ Rc $end
$var wire 1 _ S $end
$var wire 1 ` Sc $end
$upscope $end
$scope module f1 $end
$var wire 1 & CLK $end
$var wire 1 a D $end
$var wire 1 b Q $end
$var wire 1 c Qc $end
$var wire 1 d R $end
$var wire 1 % RST $end
$var wire 1 e Rc $end
$var wire 1 f S $end
$var wire 1 g Sc $end
$upscope $end
$scope module f2 $end
$var wire 1 & CLK $end
$var wire 1 h D $end
$var wire 1 i Q $end
$var wire 1 j Qc $end
$var wire 1 k R $end
$var wire 1 % RST $end
$var wire 1 l Rc $end
$var wire 1 m S $end
$var wire 1 n Sc $end
$upscope $end
$scope module f3 $end
$var wire 1 & CLK $end
$var wire 1 o D $end
$var wire 1 p Q $end
$var wire 1 q Qc $end
$var wire 1 r R $end
$var wire 1 % RST $end
$var wire 1 s Rc $end
$var wire 1 t S $end
$var wire 1 u Sc $end
$upscope $end
$scope module f4 $end
$var wire 1 & CLK $end
$var wire 1 v D $end
$var wire 1 w Q $end
$var wire 1 x Qc $end
$var wire 1 y R $end
$var wire 1 % RST $end
$var wire 1 z Rc $end
$var wire 1 { S $end
$var wire 1 | Sc $end
$upscope $end
$upscope $end
$upscope $end
$upscope $end
$enddefinitions $end
#0
$dumpvars
0|
1{
1z
1y
1x
0w
0v
0u
1t
1s
1r
1q
0p
0o
0n
1m
1l
1k
1j
0i
0h
0g
1f
1e
1d
1c
0b
0a
0`
1_
1^
1]
1\
0[
0Z
b0 Y
b0 X
b0 W
b0 V
b0 U
b0 T
b0 S
0R
1Q
1P
1O
0N
1M
1L
1K
1J
0I
1H
0G
b0 F
0E
1D
0C
1B
1A
1@
0?
1>
1=
1<
0;
1:
19
18
17
06
15
04
13
02
b0 1
10
0/
1.
0-
b0 ,
0+
b0 *
b0 )
b0 (
b0 '
0&
0%
b0 $
0#
0"
b0 !
$end
#10
08
0<
0@
0K
0O
0]
0d
0k
0r
0y
1"
1&
#20
1;
1C
09
0A
18
1<
1@
1K
1O
1]
1d
1k
1r
1y
0"
0&
1#
1+
#30
08
19
1%
0.
13
1h
07
1Z
1/
12
16
b101 )
b101 1
b101 S
b101 (
b101 T
b101 U
b101 $
b101 W
b101 X
b101 !
b101 *
0:
0<
0B
0K
0O
0]
0d
0k
0r
0y
1"
1&
#40
0/
0?
1`
1n
0;
03
1=
0^
0l
1:
18
1<
1B
1K
1O
1]
1d
1k
1r
1y
0"
0&
#50
0]
0k
1^
1l
02
b1 )
b1 1
b1 S
b1 (
b1 T
b1 U
1/
1\
0Z
1a
1j
1h
0o
13
1[
1i
b101 '
b101 V
b101 Y
b110 $
b110 W
b110 X
b110 !
b110 *
08
0<
0B
0K
0O
0_
0d
0m
0r
0y
1"
1&
#60
1?
1g
0=
0`
0\
0e
0l
0j
18
1<
1B
1K
1O
1_
1]
1d
1m
1k
1r
1y
0"
0&
#70
17
0@
1A
0d
1j
10
1e
0k
1-
1Z
0a
1l
05
0[
1c
0h
1o
14
b11 )
b11 1
b11 S
b11 (
b11 T
b11 U
1\
1b
b110 '
b110 V
b110 Y
b1001 $
b1001 W
b1001 X
b1001 !
b1001 *
08
0>
0B
0K
0O
0]
0f
0m
0r
0y
1"
1&
#80
1N
1`
1u
0A
07
0L
0^
0g
0c
0n
0j
0s
18
1>
1B
1@
1K
1O
1]
1f
1d
1m
1k
1r
1y
0"
0&
#90
0]
0r
1^
1h
1s
0H
1E
1\
0Z
0b
0i
1q
1o
0v
1G
b1 ,
b1 F
1[
1c
1j
1p
b1001 '
b1001 V
b1001 Y
b1100 $
b1100 W
b1100 X
b1100 !
b1100 *
08
0>
0B
0M
0O
0_
0d
0k
0t
0y
1"
1&
#100
1R
1n
0P
0`
0\
0l
0s
0q
18
1>
1B
1M
1O
1_
1]
1d
1k
1t
1r
1y
0"
0&
#110
17
0@
1A
00
1H
0O
1.
1q
0K
1P
0k
0r
1L
1E
1Z
1a
1l
1s
1J
1D
0[
1j
1h
1o
0v
1I
b11 ,
b11 F
1\
1i
b1100 '
b1100 V
b1100 Y
b1111 $
b1111 W
b1111 X
b1111 !
b1111 *
08
0>
0B
0M
0Q
0]
0d
0m
0t
0y
1"
1&
#120
0R
1;
0E
1`
1g
09
0C
07
0N
0H
1P
0J
0D
0^
0e
0l
0j
0s
0q
18
1>
1B
1@
1M
1K
1Q
1O
1]
1d
1m
1k
1t
1r
1y
0"
0&
#130
10
15
08
0d
0<
1q
19
1e
1=
0]
0r
1.
0a
0/
0-
1^
1s
13
06
0G
0I
b0 ,
b0 F
0E
1\
1Z
1c
0o
1v
12
b110 )
b110 1
b110 S
b110 (
b110 T
b110 U
17
1H
1J
1D
1[
1b
b1111 '
b1111 V
b1111 Y
b10101 $
b10101 W
b10101 X
b10101 !
b10101 *
0:
0>
0@
0K
0O
0_
0f
0m
0t
0y
1"
1&
#140
0;
00
0.
0C
1|
19
03
0?
05
1A
0^
0\
0g
0c
0u
0q
0z
1:
18
1>
1<
1@
1K
1O
1_
1]
1f
1d
1m
1t
1r
1y
0"
0&
#150
0Z
0h
0]
0`
0[
0k
0n
0i
0|
1^
1\
1l
1j
0%
1.
0y
10
1z
02
04
b0 )
b0 1
b0 S
b0 (
b0 T
b0 U
0b
0p
1x
0v
13
15
1c
1q
0w
b0 '
b0 V
b0 Y
b0 $
b0 W
b0 X
b0 !
b0 *
08
0<
0@
0K
0O
1_
0d
1m
0r
1{
1"
1&
#160
1;
1C
09
0A
18
1<
1@
1K
1O
1]
1d
1k
1r
1y
0"
0&
#170
08
19
1%
0.
13
1h
07
1Z
1/
12
16
b101 )
b101 1
b101 S
b101 (
b101 T
b101 U
b101 $
b101 W
b101 X
b101 !
b101 *
0:
0<
0B
0K
0O
0]
0d
0k
0r
0y
1"
1&
#180
0/
0?
1`
1n
0;
03
1=
0^
0l
1:
18
1<
1B
1K
1O
1]
1d
1k
1r
1y
0"
0&
#190
0]
0k
1^
1l
02
b1 )
b1 1
b1 S
b1 (
b1 T
b1 U
1/
1\
0Z
1a
1j
1h
0o
13
1[
1i
b101 '
b101 V
b101 Y
b110 $
b110 W
b110 X
b110 !
b110 *
08
0<
0B
0K
0O
0_
0d
0m
0r
0y
1"
1&
#200
1?
1g
0=
0`
0\
0e
0l
0j
18
1<
1B
1K
1O
1_
1]
1d
1m
1k
1r
1y
0"
0&
#210
17
0@
1A
0d
1j
10
1e
0k
1-
1Z
0a
1l
05
0[
1c
0h
1o
14
b11 )
b11 1
b11 S
b11 (
b11 T
b11 U
1\
1b
b110 '
b110 V
b110 Y
b1001 $
b1001 W
b1001 X
b1001 !
b1001 *
08
0>
0B
0K
0O
0]
0f
0m
0r
0y
1"
1&
#220
1N
1`
1u
0A
07
0L
0^
0g
0c
0n
0j
0s
18
1>
1B
1@
1K
1O
1]
1f
1d
1m
1k
1r
1y
0"
0&
#230
0]
0r
1^
1h
1s
0H
1E
1\
0Z
0b
0i
1q
1o
0v
1G
b1 ,
b1 F
1[
1c
1j
1p
b1001 '
b1001 V
b1001 Y
b1100 $
b1100 W
b1100 X
b1100 !
b1100 *
08
0>
0B
0M
0O
0_
0d
0k
0t
0y
1"
1&
#240
1R
1n
0P
0`
0\
0l
0s
0q
18
1>
1B
1M
1O
1_
1]
1d
1k
1t
1r
1y
0"
0&
#250
17
0@
1A
00
1H
0O
1.
1q
0K
1P
0k
0r
1L
1E
1Z
1a
1l
1s
1J
1D
0[
1j
1h
1o
0v
1I
b11 ,
b11 F
1\
1i
b1100 '
b1100 V
b1100 Y
b1111 $
b1111 W
b1111 X
b1111 !
b1111 *
08
0>
0B
0M
0Q
0]
0d
0m
0t
0y
1"
1&
#260
0R
1;
0E
1`
1g
09
0C
07
0N
0H
1P
0J
0D
0^
0e
0l
0j
0s
0q
18
1>
1B
1@
1M
1K
1Q
1O
1]
1d
1m
1k
1t
1r
1y
0"
0&
#270
10
15
08
0d
0<
1q
19
1e
1=
0]
0r
1.
0a
0/
0-
1^
1s
13
06
0G
0I
b0 ,
b0 F
0E
1\
1Z
1c
0o
1v
12
b110 )
b110 1
b110 S
b110 (
b110 T
b110 U
17
1H
1J
1D
1[
1b
b1111 '
b1111 V
b1111 Y
b10101 $
b10101 W
b10101 X
b10101 !
b10101 *
0:
0>
0@
0K
0O
0_
0f
0m
0t
0y
1"
1&
#280
0;
00
0.
0C
1|
19
03
0?
05
1A
0^
0\
0g
0c
0u
0q
0z
1:
18
1>
1<
1@
1K
1O
1_
1]
1f
1d
1m
1t
1r
1y
0"
0&
#290
0Z
0h
0]
0`
0[
0k
0n
0i
0|
1^
1\
1l
1j
0%
1.
0y
10
1z
02
04
b0 )
b0 1
b0 S
b0 (
b0 T
b0 U
0b
0p
1x
0v
13
15
1c
1q
0w
b0 '
b0 V
b0 Y
b0 $
b0 W
b0 X
b0 !
b0 *
08
0<
0@
0K
0O
1_
0d
1m
0r
1{
1"
1&
#300
1;
1C
09
0A
18
1<
1@
1K
1O
1]
1d
1k
1r
1y
0"
0&
#310
08
19
1%
0.
13
1h
07
1Z
1/
12
16
b101 )
b101 1
b101 S
b101 (
b101 T
b101 U
b101 $
b101 W
b101 X
b101 !
b101 *
0:
0<
0B
0K
0O
0]
0d
0k
0r
0y
1"
1&
#320
0/
0?
1`
1n
0;
03
1=
0^
0l
1:
18
1<
1B
1K
1O
1]
1d
1k
1r
1y
0"
0&
#330
0]
0k
1^
1l
02
b1 )
b1 1
b1 S
b1 (
b1 T
b1 U
1/
1\
0Z
1a
1j
1h
0o
13
1[
1i
b101 '
b101 V
b101 Y
b110 $
b110 W
b110 X
b110 !
b110 *
08
0<
0B
0K
0O
0_
0d
0m
0r
0y
1"
1&
#340
1?
1g
0=
0`
0\
0e
0l
0j
18
1<
1B
1K
1O
1_
1]
1d
1m
1k
1r
1y
0"
0&
#350
17
0@
1A
0d
1j
10
1e
0k
1-
1Z
0a
1l
05
0[
1c
0h
1o
14
b11 )
b11 1
b11 S
b11 (
b11 T
b11 U
1\
1b
b110 '
b110 V
b110 Y
b1001 $
b1001 W
b1001 X
b1001 !
b1001 *
08
0>
0B
0K
0O
0]
0f
0m
0r
0y
1"
1&
#360
1N
1`
1u
0A
07
0L
0^
0g
0c
0n
0j
0s
18
1>
1B
1@
1K
1O
1]
1f
1d
1m
1k
1r
1y
0"
0&
#370
0]
0r
1^
1h
1s
0H
1E
1\
0Z
0b
0i
1q
1o
0v
1G
b1 ,
b1 F
1[
1c
1j
1p
b1001 '
b1001 V
b1001 Y
b1100 $
b1100 W
b1100 X
b1100 !
b1100 *
08
0>
0B
0M
0O
0_
0d
0k
0t
0y
1"
1&
#380
1R
1n
0P
0`
0\
0l
0s
0q
18
1>
1B
1M
1O
1_
1]
1d
1k
1t
1r
1y
0"
0&
#390
17
0@
1A
00
1H
0O
1.
1q
0K
1P
0k
0r
1L
1E
1Z
1a
1l
1s
1J
1D
0[
1j
1h
1o
0v
1I
b11 ,
b11 F
1\
1i
b1100 '
b1100 V
b1100 Y
b1111 $
b1111 W
b1111 X
b1111 !
b1111 *
08
0>
0B
0M
0Q
0]
0d
0m
0t
0y
1"
1&
#400
0R
1;
0E
1`
1g
09
0C
07
0N
0H
1P
0J
0D
0^
0e
0l
0j
0s
0q
18
1>
1B
1@
1M
1K
1Q
1O
1]
1d
1m
1k
1t
1r
1y
0"
0&
#410
10
15
08
0d
0<
1q
19
1e
1=
0]
0r
1.
0a
0/
0-
1^
1s
13
06
0G
0I
b0 ,
b0 F
0E
1\
1Z
1c
0o
1v
12
b110 )
b110 1
b110 S
b110 (
b110 T
b110 U
17
1H
1J
1D
1[
1b
b1111 '
b1111 V
b1111 Y
b10101 $
b10101 W
b10101 X
b10101 !
b10101 *
0:
0>
0@
0K
0O
0_
0f
0m
0t
0y
1"
1&
#420
0;
00
0.
0C
1|
19
03
0?
05
1A
0^
0\
0g
0c
0u
0q
0z
1:
18
1>
1<
1@
1K
1O
1_
1]
1f
1d
1m
1t
1r
1y
0"
0&
#430
0Z
0h
0]
0`
0[
0k
0n
0i
0|
1^
1\
1l
1j
0%
1.
0y
10
1z
02
04
b0 )
b0 1
b0 S
b0 (
b0 T
b0 U
0b
0p
1x
0v
13
15
1c
1q
0w
b0 '
b0 V
b0 Y
b0 $
b0 W
b0 X
b0 !
b0 *
08
0<
0@
0K
0O
1_
0d
1m
0r
1{
1"
1&
#440
1;
1C
09
0A
18
1<
1@
1K
1O
1]
1d
1k
1r
1y
0"
0&
#450
08
19
1%
0.
13
1h
07
1Z
1/
12
16
b101 )
b101 1
b101 S
b101 (
b101 T
b101 U
b101 $
b101 W
b101 X
b101 !
b101 *
0:
0<
0B
0K
0O
0]
0d
0k
0r
0y
1"
1&
#460
0/
0?
1`
1n
0;
03
1=
0^
0l
1:
18
1<
1B
1K
1O
1]
1d
1k
1r
1y
0"
0&
#470
0]
0k
1^
1l
02
b1 )
b1 1
b1 S
b1 (
b1 T
b1 U
1/
1\
0Z
1a
1j
1h
0o
13
1[
1i
b101 '
b101 V
b101 Y
b110 $
b110 W
b110 X
b110 !
b110 *
08
0<
0B
0K
0O
0_
0d
0m
0r
0y
1"
1&
#480
1?
1g
0=
0`
0\
0e
0l
0j
18
1<
1B
1K
1O
1_
1]
1d
1m
1k
1r
1y
0"
0&
#490
17
0@
1A
0d
1j
10
1e
0k
1-
1Z
0a
1l
05
0[
1c
0h
1o
14
b11 )
b11 1
b11 S
b11 (
b11 T
b11 U
1\
1b
b110 '
b110 V
b110 Y
b1001 $
b1001 W
b1001 X
b1001 !
b1001 *
08
0>
0B
0K
0O
0]
0f
0m
0r
0y
1"
1&
#500
1N
1`
1u
0A
07
0L
0^
0g
0c
0n
0j
0s
18
1>
1B
1@
1K
1O
1]
1f
1d
1m
1k
1r
1y
0"
0&
#510
0]
0r
1^
1h
1s
0H
1E
1\
0Z
0b
0i
1q
1o
0v
1G
b1 ,
b1 F
1[
1c
1j
1p
b1001 '
b1001 V
b1001 Y
b1100 $
b1100 W
b1100 X
b1100 !
b1100 *
08
0>
0B
0M
0O
0_
0d
0k
0t
0y
1"
1&
#520
0E
0N
0G
b0 ,
b0 F
1L
1H
1.
0R
0o
0h
0/
0-
1P
0[
0`
0p
b0 '
b0 V
b0 Y
0u
0?
04
0C
06
b0 )
b0 1
b0 S
b0 (
b0 T
b0 U
b0 $
b0 W
b0 X
b0 !
b0 *
18
1M
1O
1_
1]
1d
1k
1t
1r
1y
0%
1>
1=
15
1B
1A
17
0"
0&
0#
0+
