Lab2_FlipFlop/flipflop.v
module flipflop(Q, Qc, CLK, D);
input CLK, D;
output Q, Qc;

wire S, R;
wire Sc, Rc;

assign Sc = !(Rc&S);
assign S = !(Sc&CLK);
assign R = !(Rc&CLK);
assign Rc = !(R&D);

assign Q = !(Qc&S);
assign Qc = !(Q&R);





endmodule

Lab2_FlipFlop/testbench.v
`timescale 1ns/1ns
`define CYCLE 1000
module testbench();

reg CLK, D;
wire Q, Qc;

flipflop ff(.Q(Q), .Qc(Qc), .CLK(CLK), .D(D));

//**************************** clock gen **********************//
always begin #`CYCLE CLK = ~CLK; end

initial begin
	$dumpfile("result.vcd");
	$dumpvars;
end

initial begin
#0
	CLK = 0;
	D = 0;
#1	CLK = ~CLK;
#2 CLK = ~CLK;
#2000
	D = 1;
#4000
	D = 0;
#8000 $finish;
end
endmodule

Lab2_FlipFlop/simulation/modelsim/result.vcd
$date
	Fri Nov 16 12:22:35 2018
$end
$version
	ModelSim Version 10.3c
$end
$timescale
	1ps
$end

$scope module testbench $end
$var reg 1 ! CLK $end
$var reg 1 " D $end
$var wire 1 # Q $end
$var wire 1 $ Qc $end

$scope module ff $end
$var wire 1 % CLK $end
$var wire 1 & D $end
$var wire 1 # Q $end
$var wire 1 $ Qc $end
$var wire 1 ' S $end
$var wire 1 ( R $end
$var wire 1 ) Sc $end
$var wire 1 * Rc $end
$upscope $end
$upscope $end
$enddefinitions $end
#0
$dumpvars
0!
0"
x#
x$
1'
1(
0)
1*
0&
0%
$end
#1000
1!
1%
0(
1$
0#
#3000
0!
0%
1(
#1000000
1!
1%
0(
#2000000
0!
0%
1(
#2003000
1"
1&
0*
1)
#3000000
1!
1%
0'
1#
0$
#4000000
0!
0%
1'
#5000000
1!
1%
0'
#6000000
0!
0%
1'
#6003000
0"
0&
1*
0)
#7000000
1!
1%
0(
1$
0#
#8000000
0!
0%
1(
#9000000
1!
1%
0(
#10000000
0!
0%
1(
#11000000
1!
1%
0(
#12000000
0!
0%
1(
#13000000
1!
1%
0(
#14000000
0!
0%
1(
