Lab_2state/stateMachine.v
module stateMachine(A, CLK, X, Y, RST);
input CLK, X, Y, RST;
output A;

wire D1, D2;

assign D1 = (X^Y);
assign D2 = (D1^A);
flipflop ff(.Q(A), .CLK(CLK), .D(D2), .RST(RST));


endmodule


module flipflop(Q, Qc, CLK, D, RST);
input CLK, D, RST;
output Q, Qc;

wire S, R;
wire Sc, Rc;

assign Sc = !(Rc&S);
assign S = !(Sc&CLK&RST);
assign R = !(Rc&CLK);
assign Rc = !(R&D&RST);

assign Q = !(Qc&S);
assign Qc = !(Q&R&RST);


endmodule

Lab_2state/testbench.v
`timescale 1ns/1ns
`define CYCLE 100

module testbench();
reg CLK, X, Y, RST;
wire A;

stateMachine FSM(.A(A), .CLK(CLK), .X(X), .Y(Y), .RST(RST));

always begin #`CYCLE CLK = ~CLK; end
initial begin
	$dumpfile("result.vcd");
	$dumpvars;
end
initial begin
#0
	RST = 0;
	CLK = 0;
	X = 0;
	Y = 0;
#1
	RST = 1;
#1000
	X = 1;
	Y = 0;
#2000
	X = 1;
	Y = 1;
#3000
	X = 0;
	Y = 1;
#4000
	$finish;
end
endmodule

Lab_2state/simulation/modelsim/result.vcd
$date
	Fri Nov 16 15:07:40 2018
$end
$version
	ModelSim Version 10.3c
$end
$timescale
	1ps
$end

$scope module testbench $end
$var reg 1 ! CLK $end
$var reg 1 " X $end
$var reg 1 # Y $end
$var reg 1 $ RST $end
$var wire 1 % A $end

$scope module FSM $end
$var wire 1 & CLK $end
$var wire 1 ' X $end
$var wire 1 ( Y $end
$var wire 1 ) RST $end
$var wire 1 % A $end
$var wire 1 * D1 $end
$var wire 1 + D2 $end

$scope module ff $end
$var wire 1 & CLK $end
$var wire 1 + D $end
$var wire 1 ) RST $end
$var wire 1 % Q $end
$var wire 1 , Qc $end
$var wire 1 - S $end
$var wire 1 . R $end
$var wire 1 / Sc $end
$var wire 1 0 Rc $end
$upscope $end
$upscope $end
$upscope $end
$enddefinitions $end
#0
$dumpvars
0!
0"
0#
0$
0%
0*
0+
1-
1.
0/
10
0)
0(
0'
0&
1,
$end
#1000
1$
1)
#100000
1!
1&
0.
#200000
0!
0&
1.
#300000
1!
1&
0.
#400000
0!
0&
1.
#500000
1!
1&
0.
#600000
0!
0&
1.
#700000
1!
1&
0.
#800000
0!
0&
1.
#900000
1!
1&
0.
#1000000
0!
0&
1.
#1001000
1"
1'
1*
1+
00
1/
#1100000
1!
1&
0-
1%
0+
0,
10
0.
1,
#1200000
0!
0&
1-
1.
0,
0/
#1300000
1!
1&
0.
1,
0%
1+
#1400000
0!
0&
1.
00
1/
#1500000
1!
1&
0-
1%
0+
0,
10
0.
1,
#1600000
0!
0&
1-
1.
0,
0/
#1700000
1!
1&
0.
1,
0%
1+
#1800000
0!
0&
1.
00
1/
#1900000
1!
1&
0-
1%
0+
0,
10
0.
1,
#2000000
0!
0&
1-
1.
0,
0/
#2100000
1!
1&
0.
1,
0%
1+
#2200000
0!
0&
1.
00
1/
#2300000
1!
1&
0-
1%
0+
0,
10
0.
1,
#2400000
0!
0&
1-
1.
0,
0/
#2500000
1!
1&
0.
1,
0%
1+
#2600000
0!
0&
1.
00
1/
#2700000
1!
1&
0-
1%
0+
0,
10
0.
1,
#2800000
0!
0&
1-
1.
0,
0/
#2900000
1!
1&
0.
1,
0%
1+
#3000000
0!
0&
1.
00
1/
#3001000
1#
1(
0*
0+
10
0/
#3100000
1!
1&
0.
#3200000
0!
0&
1.
#3300000
1!
1&
0.
#3400000
0!
0&
1.
#3500000
1!
1&
0.
#3600000
0!
0&
1.
#3700000
1!
1&
0.
#3800000
0!
0&
1.
#3900000
1!
1&
0.
#4000000
0!
0&
1.
#4100000
1!
1&
0.
#4200000
0!
0&
1.
#4300000
1!
1&
0.
#4400000
0!
0&
1.
#4500000
1!
1&
0.
#4600000
0!
0&
1.
#4700000
1!
1&
0.
#4800000
0!
0&
1.
#4900000
1!
1&
0.
#5000000
0!
0&
1.
#5100000
1!
1&
0.
#5200000
0!
0&
1.
#5300000
1!
1&
0.
#5400000
0!
0&
1.
#5500000
1!
1&
0.
#5600000
0!
0&
1.
#5700000
1!
1&
0.
#5800000
0!
0&
1.
#5900000
1!
1&
0.
#6000000
0!
0&
1.
#6001000
0"
0'
1*
1+
00
1/
#6100000
1!
1&
0-
1%
0+
0,
10
0.
1,
#6200000
0!
0&
1-
1.
0,
0/
#6300000
1!
1&
0.
1,
0%
1+
#6400000
0!
0&
1.
00
1/
#6500000
1!
1&
0-
1%
0+
0,
10
0.
1,
#6600000
0!
0&
1-
1.
0,
0/
#6700000
1!
1&
0.
1,
0%
1+
#6800000
0!
0&
1.
00
1/
#6900000
1!
1&
0-
1%
0+
0,
10
0.
1,
#7000000
0!
0&
1-
1.
0,
0/
#7100000
1!
1&
0.
1,
0%
1+
#7200000
0!
0&
1.
00
1/
#7300000
1!
1&
0-
1%
0+
0,
10
0.
1,
#7400000
0!
0&
1-
1.
0,
0/
#7500000
1!
1&
0.
1,
0%
1+
#7600000
0!
0&
1.
00
1/
#7700000
1!
1&
0-
1%
0+
0,
10
0.
1,
#7800000
0!
0&
1-
1.
0,
0/
#7900000
1!
1&
0.
1,
0%
1+
#8000000
0!
0&
1.
00
1/
#8100000
1!
1&
0-
1%
0+
0,
10
0.
1,
#8200000
0!
0&
1-
1.
0,
0/
#8300000
1!
1&
0.
1,
0%
1+
#8400000
0!
0&
1.
00
1/
#8500000
1!
1&
0-
1%
0+
0,
10
0.
1,
#8600000
0!
0&
1-
1.
0,
0/
#8700000
1!
1&
0.
1,
0%
1+
#8800000
0!
0&
1.
00
1/
#8900000
1!
1&
0-
1%
0+
0,
10
0.
1,
#9000000
0!
0&
1-
1.
0,
0/
#9100000
1!
1&
0.
1,
0%
1+
#9200000
0!
0&
1.
00
1/
#9300000
1!
1&
0-
1%
0+
0,
10
0.
1,
#9400000
0!
0&
1-
1.
0,
0/
#9500000
1!
1&
0.
1,
0%
1+
#9600000
0!
0&
1.
00
1/
#9700000
1!
1&
0-
1%
0+
0,
10
0.
1,
#9800000
0!
0&
1-
1.
0,
0/
#9900000
1!
1&
0.
1,
0%
1+
#10000000
0!
0&
1.
00
1/
