iverilog/final_mock1/mock1.v
module mock1(number, clk, rst);
output [2:0] number;
input clk, rst;

wire qa, qb, qc, qa_c, qb_c, qc_c;
wire da, db, dc;
wire [1:0]cnt;
wire cnt_en;

flipflop a(qa, qa_c, clk, da, rst);
flipflop b(qb, qb_c, clk, db, rst);
flipflop c(qc, qc_c, clk, dc, rst);
counter count(cnt, clk, cnt_en);
assign cnt_en = qa_c&qb&qc;
assign da = qa_c&((qb_c&qc_c)|(qb&qc&cnt[0]&cnt[1]));
assign db = qa_c&qc;
assign dc = (qa_c&qb_c)|(qc&((qa&qb_c)|(qa_c&qb&!(cnt[0]&cnt[1]))));

assign number[2] = qa;
assign number[1] = qb;
assign number[0] = qc;

endmodule

module counter(counter, clk, rst);
output [1:0]counter;
input clk, rst;

wire c0_in, c1_in;
wire q0, q1;

flipflop cnt0(q0, c0_in, clk, c0_in, rst);
flipflop cnt1(q1, , clk, c1_in, rst);

assign c1_in = q0^q1;
assign counter[0] = q0;
assign counter[1] = q1;

endmodule

module flipflop(Q, Qc, CLK, D, RST);
input CLK, D, RST;
output Q;
output Qc;

wire S, R;
wire Sc, Rc;

nand g1(Sc, Rc, S);
nand g2(S, Sc, CLK, RST);
nand g3(R, Rc, CLK);
nand g4(Rc, R, D, RST);

nand g5(Q, Qc, S);
nand g6(Qc, Q, R, RST);

endmodule

iverilog/final_mock1/testbench.v
`timescale 1ns/1ns
`define CYCLE 10

module testbench();
reg CLK, RST;
wire [2:0]num;

mock1 mock(.number(num), .clk(CLK), .rst(RST));
	
always begin #`CYCLE CLK = ~CLK; end
initial begin
	$dumpfile("result.vcd");
	$dumpvars;
end

initial begin
#0
	RST = 0;
	CLK = 0;
#20
	RST = 1;
#200
	RST = 0;
	$finish;
end
endmodule

iverilog/final_mock1/result.vcd
$date
	Fri Jan 11 13:32:04 2019
$end
$version
	Icarus Verilog
$end
$timescale
	1ns
$end
$scope module testbench $end
$var wire 3 ! num [2:0] $end
$var reg 1 " CLK $end
$var reg 1 # RST $end
$scope module mock $end
$var wire 1 $ clk $end
$var wire 2 % cnt [1:0] $end
$var wire 1 & cnt_en $end
$var wire 1 ' da $end
$var wire 1 ( db $end
$var wire 1 ) dc $end
$var wire 3 * number [2:0] $end
$var wire 1 + qa $end
$var wire 1 , qa_c $end
$var wire 1 - qb $end
$var wire 1 . qb_c $end
$var wire 1 / qc $end
$var wire 1 0 qc_c $end
$var wire 1 1 rst $end
$scope module a $end
$var wire 1 $ CLK $end
$var wire 1 ' D $end
$var wire 1 + Q $end
$var wire 1 , Qc $end
$var wire 1 2 R $end
$var wire 1 1 RST $end
$var wire 1 3 Rc $end
$var wire 1 4 S $end
$var wire 1 5 Sc $end
$upscope $end
$scope module b $end
$var wire 1 $ CLK $end
$var wire 1 ( D $end
$var wire 1 - Q $end
$var wire 1 . Qc $end
$var wire 1 6 R $end
$var wire 1 1 RST $end
$var wire 1 7 Rc $end
$var wire 1 8 S $end
$var wire 1 9 Sc $end
$upscope $end
$scope module c $end
$var wire 1 $ CLK $end
$var wire 1 ) D $end
$var wire 1 / Q $end
$var wire 1 0 Qc $end
$var wire 1 : R $end
$var wire 1 1 RST $end
$var wire 1 ; Rc $end
$var wire 1 < S $end
$var wire 1 = Sc $end
$upscope $end
$scope module count $end
$var wire 1 > c0_in $end
$var wire 1 ? c1_in $end
$var wire 1 $ clk $end
$var wire 2 @ counter [1:0] $end
$var wire 1 A q0 $end
$var wire 1 B q1 $end
$var wire 1 & rst $end
$scope module cnt0 $end
$var wire 1 $ CLK $end
$var wire 1 > D $end
$var wire 1 A Q $end
$var wire 1 > Qc $end
$var wire 1 C R $end
$var wire 1 & RST $end
$var wire 1 D Rc $end
$var wire 1 E S $end
$var wire 1 F Sc $end
$upscope $end
$scope module cnt1 $end
$var wire 1 $ CLK $end
$var wire 1 ? D $end
$var wire 1 B Q $end
$var wire 1 G Qc $end
$var wire 1 H R $end
$var wire 1 & RST $end
$var wire 1 I Rc $end
$var wire 1 J S $end
$var wire 1 K Sc $end
$upscope $end
$upscope $end
$upscope $end
$upscope $end
$enddefinitions $end
#0
$dumpvars
0K
1J
1I
1H
1G
0F
1E
1D
1C
0B
0A
b0 @
0?
1>
0=
1<
1;
1:
09
18
17
16
05
14
13
12
01
10
0/
1.
0-
1,
0+
b0 *
1)
0(
1'
0&
b0 %
0$
0#
0"
b0 !
$end
#10
02
06
0:
0C
0H
1"
1$
#20
15
1=
03
0;
12
16
1:
1C
1H
0"
0$
1#
11
#30
02
13
0'
1,
00
1(
1+
1/
b101 !
b101 *
04
06
0<
0C
0H
1"
1$
#40
0(
09
05
0,
17
14
12
16
1<
1C
1H
0"
0$
#50
0+
b1 !
b1 *
1(
1,
02
06
0<
0C
0H
1"
1$
#60
19
07
12
16
1<
1C
1H
0"
0$
#70
10
0:
1;
1)
1&
0.
1-
b11 !
b11 *
02
08
0<
0C
0H
1"
1$
#80
1F
0;
00
0D
12
18
1<
1:
1C
1H
0"
0$
#90
0C
1D
1>
1?
1A
b1 %
b1 @
02
08
0<
0E
0H
1"
1$
#100
1K
0F
0>
0I
12
18
1<
1E
1C
1H
0"
0$
#110
10
0:
1;
1)
0'
0H
1I
0A
1G
1?
1>
1B
b10 %
b10 @
02
08
0<
0C
0J
1"
1$
#120
1F
0;
00
0D
0I
0G
12
18
1<
1:
1C
1J
1H
0"
0$
#130
10
0:
1;
0)
1'
1G
0C
0H
1D
1I
1>
0?
1A
b11 %
b11 @
02
08
0<
0E
0J
1"
1$
#140
15
03
0=
00
0F
0>
0K
0G
12
18
1<
1:
1E
1C
1J
1H
0"
0$
#150
1)
1.
02
06
13
17
1'
0(
0&
1,
0/
0A
0B
b0 %
b0 @
1+
b110 !
b110 *
10
1>
1G
04
08
0:
0C
0H
1"
1$
#160
05
0)
0'
0=
13
0,
09
0.
1;
14
12
18
16
1:
1C
1H
0"
0$
#170
1'
1)
0+
0-
b0 !
b0 *
1,
1.
02
06
0:
0C
0H
1"
1$
#180
15
1=
03
0;
12
16
1:
1C
1H
0"
0$
#190
02
13
0'
1,
00
1(
1+
1/
b101 !
b101 *
04
06
0<
0C
0H
1"
1$
#200
0(
09
05
0,
17
14
12
16
1<
1C
1H
0"
0$
#210
0+
b1 !
b1 *
1(
1,
02
06
0<
0C
0H
1"
1$
#220
1'
0(
0=
0/
b0 !
b0 *
12
16
1C
1H
1<
1;
10
0"
0$
0#
01
